src/__init__.py
src/data.json
src/main.py
buck-1.6.0.dist-info/METADATA
buck-1.6.0.dist-info/WHEEL
buck-1.6.0.dist-info/entry_points.txt
buck-1.6.0.dist-info/top_level.txt
buck-1.6.0.dist-info/RECORD
